huntsville_havoc/__init__.py
huntsville_havoc/origins.py
import_ready-0.12.0.dist-info/LICENSE
import_ready-0.12.0.dist-info/METADATA
import_ready-0.12.0.dist-info/WHEEL
import_ready-0.12.0.dist-info/top_level.txt
import_ready-0.12.0.dist-info/RECORD
