Metadata-Version: 2.1
Name: import-ready
Version: 0.12.0
Summary: A simple importable Python package
Home-page: https://gitlab.com/dave.k.smith/import-ready
Author: Dave Smith
Author-email: dave.k.smith@gmail.com
License: MIT
Keywords: import package huntsville havoc testpypi travisci pytest codecov codacy
Platform: UNKNOWN
Classifier: Development Status :: 4 - Beta
Classifier: Intended Audience :: Developers
Classifier: Topic :: Software Development :: Libraries :: Python Modules
Classifier: License :: OSI Approved :: MIT License
Classifier: Natural Language :: English
Classifier: Operating System :: Microsoft :: Windows :: Windows 10
Classifier: Operating System :: POSIX :: Linux
Classifier: Programming Language :: Python :: 3.7
Requires-Dist: pytest
